iPoLNG/W1.npy
iPoLNG/W2.npy
iPoLNG/__init__.py
iPoLNG/iPoLNG.py
iPoLNG-0.0.2.dist-info/LICENSE
iPoLNG-0.0.2.dist-info/METADATA
iPoLNG-0.0.2.dist-info/WHEEL
iPoLNG-0.0.2.dist-info/top_level.txt
iPoLNG-0.0.2.dist-info/RECORD
