Metadata-Version: 2.1
Name: iPoLNG
Version: 0.0.2
Summary: An unsupervised model for the integrative analysis of single-cell multiomics data, coded in the deep universal probabilistic program Pyro
Author-email: Wenyu Zhang <wyzhangxii@link.cuhk.edu.hk>
License: GNU GENERAL PUBLIC LICENSE
Project-URL: Homepage, https://github.com/cuhklinlab/iPoLNG
Project-URL: Bug Tracker, https://github.com/cuhklinlab/iPoLNG/issues
Keywords: single-cell,multiomics,data integration
Classifier: Programming Language :: Python :: 3
Classifier: License :: OSI Approved :: GNU General Public License v3 (GPLv3)
Classifier: Operating System :: OS Independent
Requires-Python: >=3.7
License-File: LICENSE
Requires-Dist: importlib-resources
Requires-Dist: numpy
Requires-Dist: pyro-ppl
Requires-Dist: statsmodels
Requires-Dist: tqdm
